<?xml version="1.0" encoding="UTF-8"?>
			<scontroler>
			    <host ip='127.0.0.1'>
			        <usuario value='root'/>
			        <password value='matrixxx'/>
			    </host>
			    <servicio nombre='apache' nombreproceso='apache2'  puerto='80'>
			        <datosexternos>
			            <pidfile value='/var/log/apache2'/>
			        </datosexternos>
			        <commandos>
			        	<principales>
				            <inicio cmd='/etc/init.d/apache2 start'/>
				            <parada cmd='/etc/init.d/apache2 stop'/>
				            <reinicio cmd='/etc/init.d/apache2 restart'/>
			            </principales>
			            <otros>
			            	
			            </otros>
			        </commandos>
			        <descripcion>
			        asdasd
			        </descripcion>
			    </servicio>
			</scontroler>
		